Metadata-Version: 2.1
Name: T-Rag
Version: 0.1.0
Summary: Translation using retrieval augmented generation
Author: Ray Liu
License: MIT
License-File: LICENSE
